pyhton/__init__.py
pyhton/cli/__init__.py
pyhton/cli/cli.py
pyhton/cli/file_runner.py
pyhton/cli/help.py
pyhton/cli/interactive.py
pyhton/core/__init__.py
pyhton/core/interpreter.py
pyhton/core/lexer.py
pyhton/core/parser.py
pyhton/language/__init__.py
pyhton/language/python_words.py
pyhton/language/typo_engine.py
pyhton_cli-0.1.0.dist-info/METADATA
pyhton_cli-0.1.0.dist-info/WHEEL
pyhton_cli-0.1.0.dist-info/entry_points.txt
pyhton_cli-0.1.0.dist-info/top_level.txt
pyhton_cli-0.1.0.dist-info/RECORD
