Metadata-Version: 2.4
Name: pyhton-cli
Version: 0.1.0
Summary: A python based esolang where every word must be a typo
Requires-Python: >=3.13
Requires-Dist: blessed
Provides-Extra: dev
Requires-Dist: pytest>=8.4.1; extra == "dev"
